setup.py
bin/biomartian
biomartian/__init__.py
biomartian.egg-info/PKG-INFO
biomartian.egg-info/SOURCES.txt
biomartian.egg-info/dependency_links.txt
biomartian.egg-info/requires.txt
biomartian.egg-info/top_level.txt
biomartian/args/__init__.py
biomartian/args/validate_args.py
biomartian/bm_queries/__init__.py
biomartian/bm_queries/bm_query.py
biomartian/config/__init__.py
biomartian/config/cache_settings.py
biomartian/config/logging_settings.py
biomartian/config/version.py